flet_audio/__init__.py
flet_audio/audio.py
flet_audio/types.py
flet_audio-0.80.5.dist-info/licenses/LICENSE
flutter/flet_audio/analysis_options.yaml
flutter/flet_audio/pubspec.lock
flutter/flet_audio/pubspec.yaml
flutter/flet_audio/lib/flet_audio.dart
flutter/flet_audio/lib/src/audio.dart
flutter/flet_audio/lib/src/extension.dart
flutter/flet_audio/lib/src/utils/audio.dart
flet_audio-0.80.5.dist-info/METADATA
flet_audio-0.80.5.dist-info/WHEEL
flet_audio-0.80.5.dist-info/top_level.txt
flet_audio-0.80.5.dist-info/RECORD
